finailab/__init__.py
finailab/__main__.py
finailab/jupyter_notebook_config.py
finailab-0.1.0.data/data/version.py
finailab-0.1.0.data/scripts/run_finailab
finailab-0.1.0.dist-info/LICENCE.txt
finailab-0.1.0.dist-info/METADATA
finailab-0.1.0.dist-info/WHEEL
finailab-0.1.0.dist-info/entry_points.txt
finailab-0.1.0.dist-info/top_level.txt
finailab-0.1.0.dist-info/RECORD
