Metadata-Version: 2.1
Name: finailab
Version: 0.1.0
Summary: REMOTE_USER Authenticator: An Authenticator for Jupyterhub to read user information from HTTP request headers, as when running behind an authenticating proxy.
Home-page: https://github.com/tatsath/finailab
Author: Carl (https://github.com/tatsath)
Author-email: tatsatx@gmail.com
License: GPLv3
Keywords: Interactive,Interpreter,Shell,Web
Platform: Linux
Platform: Mac OS X
Classifier: Intended Audience :: Developers
Classifier: Intended Audience :: System Administrators
Classifier: Intended Audience :: Science/Research
Classifier: License :: OSI Approved :: GNU General Public License v3 (GPLv3)
Classifier: Programming Language :: Python
Classifier: Programming Language :: Python :: 3
License-File: LICENCE.txt
Requires-Dist: jupyterlab
